openbb_agents/__init__.py
openbb_agents/agent.py
openbb_agents/chains.py
openbb_agents/models.py
openbb_agents/prompts.py
openbb_agents/testing.py
openbb_agents/tools.py
openbb_agents/utils.py
openbb_agents-0.0.4.dist-info/METADATA
openbb_agents-0.0.4.dist-info/WHEEL
openbb_agents-0.0.4.dist-info/RECORD
