Metadata-Version: 2.1
Name: openbb-agents
Version: 0.0.4
Summary: LLMs X OpenBB Platform
Author: Michael Struwig
Author-email: michael.struwig@openbb.finance
Requires-Python: >=3.10,<3.12
Classifier: Programming Language :: Python :: 3
Classifier: Programming Language :: Python :: 3.10
Classifier: Programming Language :: Python :: 3.11
Requires-Dist: faiss-cpu (>=1.7.4,<2.0.0)
Requires-Dist: jupyterlab (>=4.0.9,<5.0.0)
Requires-Dist: langchain (>=0.1.17,<0.2.0)
Requires-Dist: langchain-community (>=0.0.37,<0.0.38)
Requires-Dist: langchain-openai (>=0.1.6,<0.2.0)
Requires-Dist: magentic[anthropic,litellm] (>=0.24.0,<0.25.0)
Requires-Dist: openbb (==4.1.7)
Requires-Dist: openbb-yfinance (>=1.1.5,<2.0.0)
Requires-Dist: pydantic (==2.7.1)
Requires-Dist: sentence-transformers (>=2.2.2,<3.0.0)
Requires-Dist: tiktoken (>=0.5.1,<0.6.0)
